{
    "/js/app.js": "/js/app.js",
    "/js/site.js": "/js/site.js",
    "/0.20c8a928b5f4d031ca38.hot-update.js": "/0.20c8a928b5f4d031ca38.hot-update.js",
    "/0.09133264bb21cadf3d29.hot-update.js": "/0.09133264bb21cadf3d29.hot-update.js",
    "/0.eb7f08366986bbff1307.hot-update.js": "/0.eb7f08366986bbff1307.hot-update.js",
    "/0.a888b0cf53425626e2d7.hot-update.js": "/0.a888b0cf53425626e2d7.hot-update.js",
    "/0.3e4c730a8255d8e026e3.hot-update.js": "/0.3e4c730a8255d8e026e3.hot-update.js",
    "/0.f9beb6e3ad0838293f8c.hot-update.js": "/0.f9beb6e3ad0838293f8c.hot-update.js",
    "/0.9e3d13731d2518884bf7.hot-update.js": "/0.9e3d13731d2518884bf7.hot-update.js",
    "/0.8cdc5ae81978d8db31ef.hot-update.js": "/0.8cdc5ae81978d8db31ef.hot-update.js",
    "/0.16d2b9f7f6f0971e3c83.hot-update.js": "/0.16d2b9f7f6f0971e3c83.hot-update.js",
    "/0.63588bf66fdb1df0becb.hot-update.js": "/0.63588bf66fdb1df0becb.hot-update.js",
    "/0.b7a759eecb27fd19deb0.hot-update.js": "/0.b7a759eecb27fd19deb0.hot-update.js",
    "/1.b7a759eecb27fd19deb0.hot-update.js": "/1.b7a759eecb27fd19deb0.hot-update.js",
    "/0.d8d4ed650f7a6b4d7fa8.hot-update.js": "/0.d8d4ed650f7a6b4d7fa8.hot-update.js",
    "/0.fec63ca67bc0a250303b.hot-update.js": "/0.fec63ca67bc0a250303b.hot-update.js",
    "/0.a19d910aab8d5086f8fd.hot-update.js": "/0.a19d910aab8d5086f8fd.hot-update.js",
    "/1.a19d910aab8d5086f8fd.hot-update.js": "/1.a19d910aab8d5086f8fd.hot-update.js",
    "/0.64ed92c7538a23f663fe.hot-update.js": "/0.64ed92c7538a23f663fe.hot-update.js",
    "/0.775e13ddb9f43124dea6.hot-update.js": "/0.775e13ddb9f43124dea6.hot-update.js",
    "/0.59329335dd3736a2426b.hot-update.js": "/0.59329335dd3736a2426b.hot-update.js",
    "/0.f7a764a94c2ff9035dc2.hot-update.js": "/0.f7a764a94c2ff9035dc2.hot-update.js",
    "/0.2a6599149e0b6d94a072.hot-update.js": "/0.2a6599149e0b6d94a072.hot-update.js",
    "/0.579c77bbcf1e599e6c4f.hot-update.js": "/0.579c77bbcf1e599e6c4f.hot-update.js",
    "/0.7bbf4e9dce311aa3ba74.hot-update.js": "/0.7bbf4e9dce311aa3ba74.hot-update.js",
    "/0.40e16c96b41c3974d23b.hot-update.js": "/0.40e16c96b41c3974d23b.hot-update.js",
    "/0.da0bed5f8cf5405621a2.hot-update.js": "/0.da0bed5f8cf5405621a2.hot-update.js",
    "/0.d858719b37556c47fb0c.hot-update.js": "/0.d858719b37556c47fb0c.hot-update.js",
    "/0.80bab74e61528a09c7fa.hot-update.js": "/0.80bab74e61528a09c7fa.hot-update.js",
    "/0.b359f8cc1a5dc33ae520.hot-update.js": "/0.b359f8cc1a5dc33ae520.hot-update.js",
    "/0.f59ccbc0b219d1f19e6d.hot-update.js": "/0.f59ccbc0b219d1f19e6d.hot-update.js",
    "/0.2389705188719f28b6fc.hot-update.js": "/0.2389705188719f28b6fc.hot-update.js",
    "/0.22a9652c61d0d140af2a.hot-update.js": "/0.22a9652c61d0d140af2a.hot-update.js",
    "/0.f2afbddc9982a043b6d9.hot-update.js": "/0.f2afbddc9982a043b6d9.hot-update.js",
    "/0.30530a761047bf633e3a.hot-update.js": "/0.30530a761047bf633e3a.hot-update.js",
    "/0.31a528e7e4e5773e342e.hot-update.js": "/0.31a528e7e4e5773e342e.hot-update.js",
    "/0.f97b7e2a6d934170ea9d.hot-update.js": "/0.f97b7e2a6d934170ea9d.hot-update.js",
    "/0.775af4706ab9a7dab865.hot-update.js": "/0.775af4706ab9a7dab865.hot-update.js",
    "/0.c32a0534b43ba1ba4856.hot-update.js": "/0.c32a0534b43ba1ba4856.hot-update.js",
    "/0.89f30bdb0dd6bee2455d.hot-update.js": "/0.89f30bdb0dd6bee2455d.hot-update.js",
    "/0.df83ce3412999eaf5855.hot-update.js": "/0.df83ce3412999eaf5855.hot-update.js",
    "/0.1a759c6cd096551263ff.hot-update.js": "/0.1a759c6cd096551263ff.hot-update.js",
    "/0.8e4f3af94f94cd38d33c.hot-update.js": "/0.8e4f3af94f94cd38d33c.hot-update.js",
    "/0.11bdd4d3c105f10cfaf9.hot-update.js": "/0.11bdd4d3c105f10cfaf9.hot-update.js",
    "/0.c79053131ea365008e2a.hot-update.js": "/0.c79053131ea365008e2a.hot-update.js",
    "/0.33f812a09841b454b5b7.hot-update.js": "/0.33f812a09841b454b5b7.hot-update.js",
    "/0.70d70c5637b179abb392.hot-update.js": "/0.70d70c5637b179abb392.hot-update.js",
    "/0.a3831b659122aac75f54.hot-update.js": "/0.a3831b659122aac75f54.hot-update.js",
    "/0.0b87baab8f397c4cff44.hot-update.js": "/0.0b87baab8f397c4cff44.hot-update.js",
    "/0.00e45c6a928df7c2b8f5.hot-update.js": "/0.00e45c6a928df7c2b8f5.hot-update.js",
    "/0.5ecb44f36291250b0536.hot-update.js": "/0.5ecb44f36291250b0536.hot-update.js",
    "/0.fd429fc0caa9d9e02cbe.hot-update.js": "/0.fd429fc0caa9d9e02cbe.hot-update.js",
    "/0.82ad1f5cd98ed827d9a7.hot-update.js": "/0.82ad1f5cd98ed827d9a7.hot-update.js",
    "/0.cbed70f7a158d752abb3.hot-update.js": "/0.cbed70f7a158d752abb3.hot-update.js",
    "/0.42c575065aabe3e97aa4.hot-update.js": "/0.42c575065aabe3e97aa4.hot-update.js",
    "/0.4e158f03be98e33e242c.hot-update.js": "/0.4e158f03be98e33e242c.hot-update.js",
    "/0.6d2997e7cc51b25edaef.hot-update.js": "/0.6d2997e7cc51b25edaef.hot-update.js",
    "/0.ce050ec1d676672ffcfd.hot-update.js": "/0.ce050ec1d676672ffcfd.hot-update.js",
    "/0.b0571e794f0ba5e7f25e.hot-update.js": "/0.b0571e794f0ba5e7f25e.hot-update.js",
    "/0.f41b20c555aaae84e367.hot-update.js": "/0.f41b20c555aaae84e367.hot-update.js",
    "/0.f62543a5cf835c8d7254.hot-update.js": "/0.f62543a5cf835c8d7254.hot-update.js",
    "/0.d21a9623fb2f333324b9.hot-update.js": "/0.d21a9623fb2f333324b9.hot-update.js",
    "/0.f57140a15bcd12baeb92.hot-update.js": "/0.f57140a15bcd12baeb92.hot-update.js",
    "/0.c1a6938c913ae9263714.hot-update.js": "/0.c1a6938c913ae9263714.hot-update.js",
    "/0.a22404d038de3d8e4d0c.hot-update.js": "/0.a22404d038de3d8e4d0c.hot-update.js",
    "/0.001ffb7ffd4f8531eb1e.hot-update.js": "/0.001ffb7ffd4f8531eb1e.hot-update.js",
    "/0.36d8875926b264afbcd8.hot-update.js": "/0.36d8875926b264afbcd8.hot-update.js",
    "/0.0f9e143634e74dfe70fa.hot-update.js": "/0.0f9e143634e74dfe70fa.hot-update.js",
    "/0.c56c7be5e4ce5e0dcb36.hot-update.js": "/0.c56c7be5e4ce5e0dcb36.hot-update.js",
    "/0.7d09ea106da5fb8ea699.hot-update.js": "/0.7d09ea106da5fb8ea699.hot-update.js",
    "/0.0f6392ec1a1338d31621.hot-update.js": "/0.0f6392ec1a1338d31621.hot-update.js",
    "/0.b9b1954b982e92434bfb.hot-update.js": "/0.b9b1954b982e92434bfb.hot-update.js",
    "/0.1639063e37a60974d13f.hot-update.js": "/0.1639063e37a60974d13f.hot-update.js",
    "/0.dad2753ce914c31f59bf.hot-update.js": "/0.dad2753ce914c31f59bf.hot-update.js",
    "/0.2f7d4e87ad04e0a9fa38.hot-update.js": "/0.2f7d4e87ad04e0a9fa38.hot-update.js",
    "/0.f6ffca37f8899e59d41e.hot-update.js": "/0.f6ffca37f8899e59d41e.hot-update.js",
    "/0.e66db5bf4355596e4a41.hot-update.js": "/0.e66db5bf4355596e4a41.hot-update.js",
    "/0.2cdc4c96c27a1d70e01a.hot-update.js": "/0.2cdc4c96c27a1d70e01a.hot-update.js",
    "/0.1c53dbeb37bb963370bf.hot-update.js": "/0.1c53dbeb37bb963370bf.hot-update.js",
    "/0.2e174fdfc3d10ad57f1e.hot-update.js": "/0.2e174fdfc3d10ad57f1e.hot-update.js",
    "/0.d3ab65efd9006279d36a.hot-update.js": "/0.d3ab65efd9006279d36a.hot-update.js",
    "/0.dd7a0d8249fb7394e372.hot-update.js": "/0.dd7a0d8249fb7394e372.hot-update.js",
    "/0.80dabe59b094c12d60ae.hot-update.js": "/0.80dabe59b094c12d60ae.hot-update.js",
    "/0.db05357ab931b830ac60.hot-update.js": "/0.db05357ab931b830ac60.hot-update.js",
    "/0.36f5f8358d05458a46e5.hot-update.js": "/0.36f5f8358d05458a46e5.hot-update.js",
    "/0.a62641e3365797bff0f3.hot-update.js": "/0.a62641e3365797bff0f3.hot-update.js",
    "/0.c2ad583db222bf35a0e5.hot-update.js": "/0.c2ad583db222bf35a0e5.hot-update.js",
    "/0.227d8179e3ea9c9ab00f.hot-update.js": "/0.227d8179e3ea9c9ab00f.hot-update.js",
    "/0.d2dcc76b7a3a45bdfd3c.hot-update.js": "/0.d2dcc76b7a3a45bdfd3c.hot-update.js",
    "/0.1e7402b7ebd050571157.hot-update.js": "/0.1e7402b7ebd050571157.hot-update.js",
    "/0.3620d55f877620b32258.hot-update.js": "/0.3620d55f877620b32258.hot-update.js",
    "/0.4c6da2b6f3ff414290c9.hot-update.js": "/0.4c6da2b6f3ff414290c9.hot-update.js",
    "/0.b9ff45545fed20768541.hot-update.js": "/0.b9ff45545fed20768541.hot-update.js",
    "/0.fef375263cf1a4831885.hot-update.js": "/0.fef375263cf1a4831885.hot-update.js",
    "/0.bb17b896a46cbce74a0f.hot-update.js": "/0.bb17b896a46cbce74a0f.hot-update.js",
    "/0.4b22480b71fe6620c36f.hot-update.js": "/0.4b22480b71fe6620c36f.hot-update.js",
    "/0.f575b5810fe41391aab6.hot-update.js": "/0.f575b5810fe41391aab6.hot-update.js",
    "/0.51a9d3a86f9f3ae17f26.hot-update.js": "/0.51a9d3a86f9f3ae17f26.hot-update.js",
    "/0.845ab56326d51ab57f06.hot-update.js": "/0.845ab56326d51ab57f06.hot-update.js",
    "/0.3f9e21717838b6e6e738.hot-update.js": "/0.3f9e21717838b6e6e738.hot-update.js",
    "/0.d3dd9a3e1257d62ea234.hot-update.js": "/0.d3dd9a3e1257d62ea234.hot-update.js",
    "/0.e5738d17dec3c4168df9.hot-update.js": "/0.e5738d17dec3c4168df9.hot-update.js",
    "/0.13b737968e595ccf7ad4.hot-update.js": "/0.13b737968e595ccf7ad4.hot-update.js",
    "/0.b19ba355781b0763407b.hot-update.js": "/0.b19ba355781b0763407b.hot-update.js",
    "/0.33bba19cc43f1a46b565.hot-update.js": "/0.33bba19cc43f1a46b565.hot-update.js",
    "/0.7f201cbbe17f4a580a1e.hot-update.js": "/0.7f201cbbe17f4a580a1e.hot-update.js",
    "/0.5a290787243891183615.hot-update.js": "/0.5a290787243891183615.hot-update.js",
    "/0.8ff3181edd478a989c42.hot-update.js": "/0.8ff3181edd478a989c42.hot-update.js",
    "/0.b37a9740ea20828eac24.hot-update.js": "/0.b37a9740ea20828eac24.hot-update.js",
    "/0.01d94d9a393505d55785.hot-update.js": "/0.01d94d9a393505d55785.hot-update.js",
    "/0.3a433b3c65a80516077b.hot-update.js": "/0.3a433b3c65a80516077b.hot-update.js",
    "/0.ae65bf4ec3e223540ace.hot-update.js": "/0.ae65bf4ec3e223540ace.hot-update.js",
    "/0.d7c9280521a70d92e5b5.hot-update.js": "/0.d7c9280521a70d92e5b5.hot-update.js",
    "/0.9d4a914916eb1592af49.hot-update.js": "/0.9d4a914916eb1592af49.hot-update.js",
    "/0.fbb7ce8a263172005a14.hot-update.js": "/0.fbb7ce8a263172005a14.hot-update.js",
    "/0.de3f2033fd2bdea507fd.hot-update.js": "/0.de3f2033fd2bdea507fd.hot-update.js",
    "/0.4616a9c1119258ba5f75.hot-update.js": "/0.4616a9c1119258ba5f75.hot-update.js",
    "/0.d14460d845a371d75caf.hot-update.js": "/0.d14460d845a371d75caf.hot-update.js",
    "/0.f3be2409ac95b6480c05.hot-update.js": "/0.f3be2409ac95b6480c05.hot-update.js",
    "/0.e1987b058dd94109c61a.hot-update.js": "/0.e1987b058dd94109c61a.hot-update.js",
    "/0.f4791407aa578c9842f9.hot-update.js": "/0.f4791407aa578c9842f9.hot-update.js",
    "/0.deb6e1e782970de4fc44.hot-update.js": "/0.deb6e1e782970de4fc44.hot-update.js",
    "/0.231bbb4fc7ba3c94ab7e.hot-update.js": "/0.231bbb4fc7ba3c94ab7e.hot-update.js",
    "/0.8e16401ad72a0916326a.hot-update.js": "/0.8e16401ad72a0916326a.hot-update.js",
    "/0.1fee62cfd052e10b7a20.hot-update.js": "/0.1fee62cfd052e10b7a20.hot-update.js",
    "/0.179404d051b16ff2638e.hot-update.js": "/0.179404d051b16ff2638e.hot-update.js",
    "/0.e2bb3f74c8befd6fa870.hot-update.js": "/0.e2bb3f74c8befd6fa870.hot-update.js",
    "/0.aa9e10679af5b6b3e3a9.hot-update.js": "/0.aa9e10679af5b6b3e3a9.hot-update.js",
    "/0.aa3d19a33db05047348e.hot-update.js": "/0.aa3d19a33db05047348e.hot-update.js",
    "/0.ee4b94c31a688a6f17fe.hot-update.js": "/0.ee4b94c31a688a6f17fe.hot-update.js",
    "/0.e59a8a38a584b22ce615.hot-update.js": "/0.e59a8a38a584b22ce615.hot-update.js",
    "/0.18caf473b2707fa24cd8.hot-update.js": "/0.18caf473b2707fa24cd8.hot-update.js",
    "/0.975fabc3823f3f2ca7d0.hot-update.js": "/0.975fabc3823f3f2ca7d0.hot-update.js",
    "/0.e3255bc68ffbb20a588c.hot-update.js": "/0.e3255bc68ffbb20a588c.hot-update.js",
    "/0.cc7065202623e8d299dc.hot-update.js": "/0.cc7065202623e8d299dc.hot-update.js",
    "/0.a7e6d8562cde0070484f.hot-update.js": "/0.a7e6d8562cde0070484f.hot-update.js",
    "/0.c1a00c9be9eeb5d1f4a5.hot-update.js": "/0.c1a00c9be9eeb5d1f4a5.hot-update.js",
    "/0.d81d88e75a3c0e19a201.hot-update.js": "/0.d81d88e75a3c0e19a201.hot-update.js",
    "/0.082eefedf0affea4e2e2.hot-update.js": "/0.082eefedf0affea4e2e2.hot-update.js",
    "/0.36f2fbaab077e428c4bd.hot-update.js": "/0.36f2fbaab077e428c4bd.hot-update.js",
    "/0.4ef14dbb147ab316c40a.hot-update.js": "/0.4ef14dbb147ab316c40a.hot-update.js",
    "/0.f38a510758611deb409f.hot-update.js": "/0.f38a510758611deb409f.hot-update.js",
    "/0.1b4f97c03c5aed611ff6.hot-update.js": "/0.1b4f97c03c5aed611ff6.hot-update.js",
    "/0.5334ca23965d9e8db0a1.hot-update.js": "/0.5334ca23965d9e8db0a1.hot-update.js",
    "/0.13bb72a51474fa0723f5.hot-update.js": "/0.13bb72a51474fa0723f5.hot-update.js",
    "/0.6d92dd7835f6e5efda41.hot-update.js": "/0.6d92dd7835f6e5efda41.hot-update.js",
    "/0.f1fa94932597696ba0fc.hot-update.js": "/0.f1fa94932597696ba0fc.hot-update.js",
    "/0.ff376cd07ba749c28463.hot-update.js": "/0.ff376cd07ba749c28463.hot-update.js",
    "/0.687dc8c5746a62144f61.hot-update.js": "/0.687dc8c5746a62144f61.hot-update.js",
    "/0.13af9730a3320890f361.hot-update.js": "/0.13af9730a3320890f361.hot-update.js",
    "/0.7543a242e090c0d4fcd1.hot-update.js": "/0.7543a242e090c0d4fcd1.hot-update.js",
    "/0.821b61b0d974c5aa933b.hot-update.js": "/0.821b61b0d974c5aa933b.hot-update.js",
    "/0.7f5839eedd2fc88bfe42.hot-update.js": "/0.7f5839eedd2fc88bfe42.hot-update.js",
    "/0.4e40207f4d9d26a4a3e9.hot-update.js": "/0.4e40207f4d9d26a4a3e9.hot-update.js",
    "/0.95ca0754fa9469e00212.hot-update.js": "/0.95ca0754fa9469e00212.hot-update.js",
    "/0.e6634a73f12a70934646.hot-update.js": "/0.e6634a73f12a70934646.hot-update.js",
    "/0.6249f5956572138f6674.hot-update.js": "/0.6249f5956572138f6674.hot-update.js",
    "/0.41001026ea1cbbe39fed.hot-update.js": "/0.41001026ea1cbbe39fed.hot-update.js",
    "/0.bc3edce1c75172e2ce37.hot-update.js": "/0.bc3edce1c75172e2ce37.hot-update.js",
    "/0.6f40baaadfcb1e52db94.hot-update.js": "/0.6f40baaadfcb1e52db94.hot-update.js",
    "/0.8d3609a9c9af8f4b462a.hot-update.js": "/0.8d3609a9c9af8f4b462a.hot-update.js",
    "/0.d98546bf2caefbc73265.hot-update.js": "/0.d98546bf2caefbc73265.hot-update.js",
    "/0.e0d72faf9d5cdb349919.hot-update.js": "/0.e0d72faf9d5cdb349919.hot-update.js",
    "/0.8c98e4c972f51b0311d0.hot-update.js": "/0.8c98e4c972f51b0311d0.hot-update.js",
    "/0.cf65e5d12ecf656d9de3.hot-update.js": "/0.cf65e5d12ecf656d9de3.hot-update.js",
    "/0.6a21cccfca5b499d1792.hot-update.js": "/0.6a21cccfca5b499d1792.hot-update.js",
    "/0.9784da9c7769ba2bd478.hot-update.js": "/0.9784da9c7769ba2bd478.hot-update.js",
    "/0.4fd71e7f89bfe419e590.hot-update.js": "/0.4fd71e7f89bfe419e590.hot-update.js",
    "/0.25cc8fa71daa36865c8a.hot-update.js": "/0.25cc8fa71daa36865c8a.hot-update.js",
    "/0.24131051fd937c06fb56.hot-update.js": "/0.24131051fd937c06fb56.hot-update.js",
    "/0.4c56ce46ae9cd376bd08.hot-update.js": "/0.4c56ce46ae9cd376bd08.hot-update.js",
    "/0.363768f231a94e30777b.hot-update.js": "/0.363768f231a94e30777b.hot-update.js",
    "/0.4dc38e54e8193e37fae8.hot-update.js": "/0.4dc38e54e8193e37fae8.hot-update.js",
    "/0.ec7c8524a68ea3bfe5a2.hot-update.js": "/0.ec7c8524a68ea3bfe5a2.hot-update.js",
    "/0.8e677b39625319cc695a.hot-update.js": "/0.8e677b39625319cc695a.hot-update.js",
    "/0.be090b0d638275effde2.hot-update.js": "/0.be090b0d638275effde2.hot-update.js",
    "/0.19576322b3a2758d91b3.hot-update.js": "/0.19576322b3a2758d91b3.hot-update.js",
    "/0.6fc24a4bd0499f90006f.hot-update.js": "/0.6fc24a4bd0499f90006f.hot-update.js",
    "/0.e9eb405add64773bc85c.hot-update.js": "/0.e9eb405add64773bc85c.hot-update.js",
    "/0.25537e807b84714b0bff.hot-update.js": "/0.25537e807b84714b0bff.hot-update.js",
    "/0.e6f9b0cecb4789961c3c.hot-update.js": "/0.e6f9b0cecb4789961c3c.hot-update.js",
    "/0.fb8db0f93b6181c92165.hot-update.js": "/0.fb8db0f93b6181c92165.hot-update.js",
    "/0.e2c311802555adb84575.hot-update.js": "/0.e2c311802555adb84575.hot-update.js",
    "/0.4849149a38ad27eb499c.hot-update.js": "/0.4849149a38ad27eb499c.hot-update.js",
    "/0.bee7fb0e7f7b6789916d.hot-update.js": "/0.bee7fb0e7f7b6789916d.hot-update.js",
    "/0.8009e25d8e2ea420e687.hot-update.js": "/0.8009e25d8e2ea420e687.hot-update.js",
    "/0.10717858a5f3b53c34c9.hot-update.js": "/0.10717858a5f3b53c34c9.hot-update.js",
    "/0.de31e3c78d47ce7bf0a6.hot-update.js": "/0.de31e3c78d47ce7bf0a6.hot-update.js",
    "/0.abf0c57f9ffd5c48d7b4.hot-update.js": "/0.abf0c57f9ffd5c48d7b4.hot-update.js",
    "/0.c15c5bac79cd07fa094f.hot-update.js": "/0.c15c5bac79cd07fa094f.hot-update.js",
    "/0.551ebae0b5d59f7c306a.hot-update.js": "/0.551ebae0b5d59f7c306a.hot-update.js",
    "/0.47c2446654b4ae724b21.hot-update.js": "/0.47c2446654b4ae724b21.hot-update.js",
    "/0.7645b48150e35592deff.hot-update.js": "/0.7645b48150e35592deff.hot-update.js",
    "/0.56c0911c422aee6b5881.hot-update.js": "/0.56c0911c422aee6b5881.hot-update.js",
    "/0.328415ab48b134a1da20.hot-update.js": "/0.328415ab48b134a1da20.hot-update.js",
    "/0.503dd66ec9c0c6541d6c.hot-update.js": "/0.503dd66ec9c0c6541d6c.hot-update.js",
    "/0.d1830f4bb3010145c546.hot-update.js": "/0.d1830f4bb3010145c546.hot-update.js",
    "/0.6da389b5df560c3a618e.hot-update.js": "/0.6da389b5df560c3a618e.hot-update.js",
    "/0.bceb01329e0788fdde39.hot-update.js": "/0.bceb01329e0788fdde39.hot-update.js",
    "/0.76e030f947de94dca39c.hot-update.js": "/0.76e030f947de94dca39c.hot-update.js",
    "/0.5551a183e3f719935abc.hot-update.js": "/0.5551a183e3f719935abc.hot-update.js",
    "/0.d497a6bce11ed8ead4f0.hot-update.js": "/0.d497a6bce11ed8ead4f0.hot-update.js",
    "/0.1579594dc006cac9a30b.hot-update.js": "/0.1579594dc006cac9a30b.hot-update.js",
    "/0.4ff12b6bbe9fb23efb23.hot-update.js": "/0.4ff12b6bbe9fb23efb23.hot-update.js",
    "/0.20d7c5a794de5eec0c04.hot-update.js": "/0.20d7c5a794de5eec0c04.hot-update.js",
    "/0.6020acdd83b067354d93.hot-update.js": "/0.6020acdd83b067354d93.hot-update.js",
    "/0.09c7f655cfafb8f25fe6.hot-update.js": "/0.09c7f655cfafb8f25fe6.hot-update.js",
    "/0.0d49614f03ff449c3f83.hot-update.js": "/0.0d49614f03ff449c3f83.hot-update.js",
    "/0.373a892a2eb04b2030d1.hot-update.js": "/0.373a892a2eb04b2030d1.hot-update.js",
    "/0.adc1bb74182995bbeb32.hot-update.js": "/0.adc1bb74182995bbeb32.hot-update.js",
    "/0.8afa156dfe842b1749e0.hot-update.js": "/0.8afa156dfe842b1749e0.hot-update.js",
    "/0.7acd475ecd616c01136a.hot-update.js": "/0.7acd475ecd616c01136a.hot-update.js",
    "/0.0ff7756ea48abb8b5105.hot-update.js": "/0.0ff7756ea48abb8b5105.hot-update.js",
    "/0.f03412507e7133ee596c.hot-update.js": "/0.f03412507e7133ee596c.hot-update.js",
    "/0.bbe1efc5fcaf135b69c3.hot-update.js": "/0.bbe1efc5fcaf135b69c3.hot-update.js",
    "/0.c6af661b8b44940fd321.hot-update.js": "/0.c6af661b8b44940fd321.hot-update.js",
    "/0.b8a00dd2e5ab3c114be3.hot-update.js": "/0.b8a00dd2e5ab3c114be3.hot-update.js",
    "/0.3e559bb2981b934db975.hot-update.js": "/0.3e559bb2981b934db975.hot-update.js",
    "/0.cf407ed76dbef3c85748.hot-update.js": "/0.cf407ed76dbef3c85748.hot-update.js",
    "/0.4a830ab340a69b1b0c9f.hot-update.js": "/0.4a830ab340a69b1b0c9f.hot-update.js",
    "/0.c5a444c161064869993a.hot-update.js": "/0.c5a444c161064869993a.hot-update.js",
    "/0.5751dd3b2512634d28b6.hot-update.js": "/0.5751dd3b2512634d28b6.hot-update.js",
    "/0.16e1901db9cb938db839.hot-update.js": "/0.16e1901db9cb938db839.hot-update.js",
    "/0.4b8371111c8ac92696d6.hot-update.js": "/0.4b8371111c8ac92696d6.hot-update.js",
    "/0.d3af561244927d9144e0.hot-update.js": "/0.d3af561244927d9144e0.hot-update.js",
    "/0.527ad558d81d8cb5df53.hot-update.js": "/0.527ad558d81d8cb5df53.hot-update.js"
}
